awesome_mixins/__init__.py
awesome_mixins/admin.py
awesome_mixins/apps.py
awesome_mixins/models.py
awesome_mixins/tests.py
awesome_mixins/views.py
awesome_mixins/management/__init__.py
awesome_mixins/management/commands/__init__.py
awesome_mixins/management/commands/generate_static_files.py
awesome_mixins/migrations/__init__.py
awesome_mixins/mixins/__init__.py
awesome_mixins/mixins/generics.py
awesome_mixins/mixins/list.py
awesome_mixins/static/awesome_mixins/css/list_view.css
awesome_mixins/static/awesome_mixins/css/list_view.css.map
awesome_mixins/static/awesome_mixins/js/twbs-pagination/.gitignore
awesome_mixins/static/awesome_mixins/js/twbs-pagination/Gruntfile.js
awesome_mixins/static/awesome_mixins/js/twbs-pagination/LICENSE
awesome_mixins/static/awesome_mixins/js/twbs-pagination/README.md
awesome_mixins/static/awesome_mixins/js/twbs-pagination/bower.json
awesome_mixins/static/awesome_mixins/js/twbs-pagination/jquery.twbsPagination.js
awesome_mixins/static/awesome_mixins/js/twbs-pagination/jquery.twbsPagination.min.js
awesome_mixins/static/awesome_mixins/js/twbs-pagination/package.json
awesome_mixins/static/awesome_mixins/js/twbs-pagination/twbs-pagination.jquery.json
awesome_mixins/static/awesome_mixins/js/twbs-pagination/examples/bootstrap-v4.html
awesome_mixins/static/awesome_mixins/js/twbs-pagination/examples/index.html
awesome_mixins/static/awesome_mixins/js/twbs-pagination/tests/index.html
awesome_mixins/static/awesome_mixins/js/twbs-pagination/tests/run-test-jquery-1.8.1.html
awesome_mixins/static/awesome_mixins/js/twbs-pagination/tests/run-test-jquery-latest.html
awesome_mixins/static/awesome_mixins/js/twbs-pagination/tests/test.js
awesome_mixins/static/awesome_mixins/sass/list_view.sass
awesome_mixins/utils/__init__.py
awesome_mixins/utils/geral.py
awesome_mixins-0.16.dist-info/DESCRIPTION.rst
awesome_mixins-0.16.dist-info/METADATA
awesome_mixins-0.16.dist-info/RECORD
awesome_mixins-0.16.dist-info/WHEEL
awesome_mixins-0.16.dist-info/metadata.json
awesome_mixins-0.16.dist-info/top_level.txt
